pymongoagg.py
PyMongoAgg-0.0.2.dist-info/METADATA
PyMongoAgg-0.0.2.dist-info/WHEEL
PyMongoAgg-0.0.2.dist-info/top_level.txt
PyMongoAgg-0.0.2.dist-info/RECORD
