Metadata-Version: 2.1
Name: PyMongoAgg
Version: 0.0.2
Summary: A Python-MongoDB Aggregation transpiler.
Author-email: Julius Park <juliusgeo@gmail.com>
Project-URL: Homepage, https://github.com/juliusgeo/PyMongoAgg
Classifier: Programming Language :: Python :: 3
Classifier: License :: OSI Approved :: MIT License
Classifier: Operating System :: OS Independent
Requires-Python: >=3.9
